pysr/.gitignore
pysr/__init__.py
pysr/__main__.py
pysr/denoising.py
pysr/deprecated.py
pysr/export.py
pysr/export_jax.py
pysr/export_latex.py
pysr/export_numpy.py
pysr/export_sympy.py
pysr/export_torch.py
pysr/expression_specs.py
pysr/feature_selection.py
pysr/julia_extensions.py
pysr/julia_helpers.py
pysr/julia_import.py
pysr/julia_registry_helpers.py
pysr/juliapkg.json
pysr/logger_specs.py
pysr/param_groupings.yml
pysr/sklearn_monkeypatch.py
pysr/sr.py
pysr/utils.py
pysr/_cli/__init__.py
pysr/_cli/main.py
pysr/test/__init__.py
pysr/test/__main__.py
pysr/test/generate_dev_juliapkg.py
pysr/test/nb_sanitize.cfg
pysr/test/params.py
pysr/test/test_cli.py
pysr/test/test_dev.py
pysr/test/test_dev_pysr.dockerfile
pysr/test/test_jax.py
pysr/test/test_main.py
pysr/test/test_nb.ipynb
pysr/test/test_startup.py
pysr/test/test_torch.py
pysr-1.5.9.dist-info/METADATA
pysr-1.5.9.dist-info/WHEEL
pysr-1.5.9.dist-info/licenses/LICENSE
pysr-1.5.9.dist-info/RECORD
