Metadata-Version: 2.4
Name: pysr
Version: 1.5.9
Summary: Simple and efficient symbolic regression
Author-email: Miles Cranmer <miles.cranmer@gmail.com>
License:                                  Apache License
License-File: LICENSE
Classifier: License :: OSI Approved :: Apache Software License
Classifier: Operating System :: OS Independent
Classifier: Programming Language :: Python :: 3
Requires-Python: >=3.8
Requires-Dist: click<9.0.0,>=7.0.0
Requires-Dist: juliacall<0.9.27,>=0.9.24
Requires-Dist: numpy<3.0.0,>=1.13.0
Requires-Dist: pandas<3.0.0,>=0.21.0
Requires-Dist: scikit-learn<2.0.0,>=1.0.0
Requires-Dist: sympy<2.0.0,>=1.0.0
Requires-Dist: typing-extensions<5.0.0,>=4.0.0
Provides-Extra: dev
Requires-Dist: beartype<0.22,>=0.19; extra == 'dev'
Requires-Dist: coverage<8,>=7; extra == 'dev'
Requires-Dist: ipykernel<7,>=6; extra == 'dev'
Requires-Dist: ipython<9,>=8; extra == 'dev'
Requires-Dist: jax[cpu]<0.6,>=0.4; extra == 'dev'
Requires-Dist: jupyter<2,>=1; extra == 'dev'
Requires-Dist: mypy<2,>=1; extra == 'dev'
Requires-Dist: nbval<0.12,>=0.11; extra == 'dev'
Requires-Dist: pandas-stubs; extra == 'dev'
Requires-Dist: pre-commit<5,>=3.0; extra == 'dev'
Requires-Dist: pytest-cov<7,>=5; extra == 'dev'
Requires-Dist: pytest<9,>=8; extra == 'dev'
Requires-Dist: tensorboard<3,>=2; extra == 'dev'
Requires-Dist: torch<3,>=2; extra == 'dev'
Requires-Dist: types-openpyxl; extra == 'dev'
Requires-Dist: types-pytz; extra == 'dev'
